consonance/__init__.py
consonance/handshake.py
consonance/protocol.py
consonance/transport.py
consonance/certman/__init__.py
consonance/certman/certman.py
consonance/config/__init__.py
consonance/config/appversion.py
consonance/config/client.py
consonance/config/useragent.py
consonance/config/templates/__init__.py
consonance/config/templates/useragent_samsung_s9p.py
consonance/config/templates/useragent_vbox.py
consonance/dissononce_extras/__init__.py
consonance/dissononce_extras/processing/__init__.py
consonance/dissononce_extras/processing/symmetricstate_wa.py
consonance/exceptions/__init__.py
consonance/exceptions/handshake_failed_exception.py
consonance/exceptions/new_rs_exception.py
consonance/proto/__init__.py
consonance/proto/wa20_pb2.py
consonance/streams/__init__.py
consonance/streams/arbitrary/__init__.py
consonance/streams/arbitrary/arbitrary.py
consonance/streams/arbitrary/arbitrary_socket.py
consonance/streams/segmented/__init__.py
consonance/streams/segmented/blockingqueue.py
consonance/streams/segmented/dummy.py
consonance/streams/segmented/segmented.py
consonance/streams/segmented/wa.py
consonance/structs/__init__.py
consonance/structs/keypair.py
consonance/structs/privatekey.py
consonance/structs/publickey.py
consonance/util/__init__.py
consonance/util/byte.py
consonance-0.1.5.dist-info/LICENSE
consonance-0.1.5.dist-info/METADATA
consonance-0.1.5.dist-info/WHEEL
consonance-0.1.5.dist-info/top_level.txt
consonance-0.1.5.dist-info/RECORD
